awscm/__init__.py
awscm/awstools.py
awscm/gluetools.py
awscm/tweeter.py
awscm/utils.py
awscm-0.3a0.dist-info/LICENSE
awscm-0.3a0.dist-info/METADATA
awscm-0.3a0.dist-info/WHEEL
awscm-0.3a0.dist-info/top_level.txt
awscm-0.3a0.dist-info/RECORD
