Metadata-Version: 2.1
Name: awscm
Version: 0.3a0
Summary: a module for easy monitoring of aws jobs and services.
Home-page: https://github.com/shubhsboson/awscm
Author: shubhsboson
Author-email: contact@shubhsboson.com
License: UNKNOWN
Project-URL: Bug Tracker, https://github.com/shubhsboson/awscm/issues
Keywords: aws,glue,lambda
Platform: UNKNOWN
Classifier: Programming Language :: Python :: 3
Classifier: Programming Language :: Python :: 3.8
Classifier: License :: OSI Approved :: MIT License
Classifier: Operating System :: OS Independent
Requires-Python: >=3.6
License-File: LICENSE
Requires-Dist: boto3
Requires-Dist: logger
Provides-Extra: dev
Requires-Dist: twine ; extra == 'dev'
